{"sprites": [{"resource_uri": "/api/v1/sprite/496/", "name": "snivy"}], "ev_yield": "", "defense": 55, "height": "6", "hp": 45, "weight": "81", "catch_rate": 0, "abilities": [{"resource_uri": "/api/v1/ability/65/", "name": "overgrow"}, {"resource_uri": "/api/v1/ability/126/", "name": "contrary"}], "sp_atk": 45, "name": "Snivy", "moves": [{"resource_uri": "/api/v1/move/402/", "learn_type": "tutor", "name": "Seed-bomb"}, {"resource_uri": "/api/v1/move/401/", "learn_type": "tutor", "name": "Aqua-tail"}, {"resource_uri": "/api/v1/move/388/", "learn_type": "tutor", "name": "Worry-seed"}, {"resource_uri": "/api/v1/move/289/", "learn_type": "tutor", "name": "Snatch"}, {"resource_uri": "/api/v1/move/282/", "learn_type": "tutor", "name": "Knock-off"}, {"resource_uri": "/api/v1/move/235/", "learn_type": "tutor", "name": "Synthesis"}, {"resource_uri": "/api/v1/move/214/", "learn_type": "tutor", "name": "Sleep-talk"}, {"resource_uri": "/api/v1/move/173/", "learn_type": "tutor", "name": "Snore"}, {"resource_uri": "/api/v1/move/20/", "learn_type": "tutor", "name": "Bind"}, {"resource_uri": "/api/v1/move/536/", "level": 16, "learn_type": "level up", "name": "Leaf-tornado"}, {"resource_uri": "/api/v1/move/520/", "learn_type": "tutor", "name": "Grass-pledge"}, {"resource_uri": "/api/v1/move/496/", "learn_type": "machine", "name": "Round"}, {"resource_uri": "/api/v1/move/489/", "level": 31, "learn_type": "level up", "name": "Coil"}, {"resource_uri": "/api/v1/move/447/", "learn_type": "machine", "name": "Grass-knot"}, {"resource_uri": "/api/v1/move/445/", "learn_type": "egg move", "name": "Captivate"}, {"resource_uri": "/api/v1/move/437/", "level": 43, "learn_type": "level up", "name": "Leaf-storm"}, {"resource_uri": "/api/v1/move/412/", "learn_type": "machine", "name": "Energy-ball"}, {"resource_uri": "/api/v1/move/380/", "level": 40, "learn_type": "level up", "name": "Gastro-acid"}, {"resource_uri": "/api/v1/move/378/", "level": 37, "learn_type": "level up", "name": "Wring-out"}, {"resource_uri": "/api/v1/move/363/", "learn_type": "egg move", "name": "Natural-gift"}, {"resource_uri": "/api/v1/move/348/", "level": 28, "learn_type": "level up", "name": "Leaf-blade"}, {"resource_uri": "/api/v1/move/347/", "learn_type": "machine", "name": "Calm-mind"}, {"resource_uri": "/api/v1/move/345/", "learn_type": "egg move", "name": "Magical-leaf"}, {"resource_uri": "/api/v1/move/332/", "learn_type": "machine", "name": "Aerial-ace"}, {"resource_uri": "/api/v1/move/269/", "learn_type": "machine", "name": "Taunt"}, {"resource_uri": "/api/v1/move/263/", "learn_type": "machine", "name": "Facade"}, {"resource_uri": "/api/v1/move/259/", "learn_type": "machine", "name": "Torment"}, {"resource_uri": "/api/v1/move/243/", "learn_type": "egg move", "name": "Mirror-coat"}, {"resource_uri": "/api/v1/move/241/", "learn_type": "machine", "name": "Sunny-day"}, {"resource_uri": "/api/v1/move/239/", "learn_type": "egg move", "name": "Twister"}, {"resource_uri": "/api/v1/move/237/", "learn_type": "machine", "name": "Hidden-power"}, {"resource_uri": "/api/v1/move/231/", "learn_type": "egg move", "name": "Iron-tail"}, {"resource_uri": "/api/v1/move/230/", "learn_type": "egg move", "name": "Sweet-scent"}, {"resource_uri": "/api/v1/move/228/", "learn_type": "egg move", "name": "Pursuit"}, {"resource_uri": "/api/v1/move/219/", "learn_type": "machine", "name": "Safeguard"}, {"resource_uri": "/api/v1/move/218/", "learn_type": "machine", "name": "Frustration"}, {"resource_uri": "/api/v1/move/216/", "learn_type": "machine", "name": "Return"}, {"resource_uri": "/api/v1/move/213/", "learn_type": "machine", "name": "Attract"}, {"resource_uri": "/api/v1/move/212/", "learn_type": "egg move", "name": "Mean-look"}, {"resource_uri": "/api/v1/move/207/", "learn_type": "machine", "name": "Swagger"}, {"resource_uri": "/api/v1/move/202/", "level": 34, "learn_type": "level up", "name": "Giga-drain"}, {"resource_uri": "/api/v1/move/182/", "learn_type": "machine", "name": "Protect"}, {"resource_uri": "/api/v1/move/164/", "learn_type": "machine", "name": "Substitute"}, {"resource_uri": "/api/v1/move/156/", "learn_type": "machine", "name": "Rest"}, {"resource_uri": "/api/v1/move/148/", "learn_type": "machine", "name": "Flash"}, {"resource_uri": "/api/v1/move/137/", "learn_type": "egg move", "name": "Glare"}, {"resource_uri": "/api/v1/move/115/", "learn_type": "machine", "name": "Reflect"}, {"resource_uri": "/api/v1/move/113/", "learn_type": "machine", "name": "Light-screen"}, {"resource_uri": "/api/v1/move/104/", "learn_type": "machine", "name": "Double-team"}, {"resource_uri": "/api/v1/move/92/", "learn_type": "machine", "name": "Toxic"}, {"resource_uri": "/api/v1/move/76/", "learn_type": "machine", "name": "Solarbeam"}, {"resource_uri": "/api/v1/move/74/", "level": 13, "learn_type": "level up", "name": "Growth"}, {"resource_uri": "/api/v1/move/73/", "level": 19, "learn_type": "level up", "name": "Leech-seed"}, {"resource_uri": "/api/v1/move/72/", "level": 22, "learn_type": "level up", "name": "Mega-drain"}, {"resource_uri": "/api/v1/move/43/", "level": 4, "learn_type": "level up", "name": "Leer"}, {"resource_uri": "/api/v1/move/35/", "level": 10, "learn_type": "level up", "name": "Wrap"}, {"resource_uri": "/api/v1/move/33/", "level": 1, "learn_type": "level up", "name": "Tackle"}, {"resource_uri": "/api/v1/move/22/", "level": 7, "learn_type": "level up", "name": "Vine-whip"}, {"resource_uri": "/api/v1/move/21/", "level": 25, "learn_type": "level up", "name": "Slam"}, {"resource_uri": "/api/v1/move/15/", "learn_type": "machine", "name": "Cut"}, {"resource_uri": "/api/v1/move/14/", "learn_type": "machine", "name": "Swords-dance"}], "speed": 63, "egg_cycles": 0, "types": [{"resource_uri": "/api/v1/type/12/", "name": "grass"}], "egg_groups": [{"resource_uri": "/api/v1/egg/5/", "name": "Ground"}, {"resource_uri": "/api/v1/egg/7/", "name": "Plant"}], "male_female_ratio": "", "resource_uri": "/api/v1/pokemon/495/", "exp": 62, "happiness": 0, "pkdx_id": 495, "growth_rate": "", "species": "", "evolutions": [{"resource_uri": "/api/v1/pokemon/496/", "method": "level_up", "level": 17, "to": "Servine"}], "descriptions": [{"resource_uri": "/api/v1/description/5865/", "name": "snivy_gen_4"}, {"resource_uri": "/api/v1/description/5866/", "name": "snivy_gen_4"}, {"resource_uri": "/api/v1/description/5867/", "name": "snivy_gen_5"}], "attack": 45, "total": 0, "modified": "2013-11-23T13:13:40.856574", "sp_def": 55, "created": "2013-11-03T15:05:42.143629", "national_id": 495}