{"sprites": [{"resource_uri": "/api/v1/sprite/683/", "name": "spritzee"}], "ev_yield": "", "defense": 60, "height": "0", "hp": 78, "weight": "0", "catch_rate": 0, "abilities": [{"resource_uri": "/api/v1/ability/131/", "name": "healer"}, {"resource_uri": "/api/v1/ability/166/", "name": "aroma-veil"}], "sp_atk": 63, "name": "Spritzee", "moves": [], "speed": 23, "egg_cycles": 0, "types": [{"resource_uri": "/api/v1/type/18/", "name": "fairy"}], "egg_groups": [{"resource_uri": "/api/v1/egg/6/", "name": "Fairy"}], "male_female_ratio": "", "resource_uri": "/api/v1/pokemon/682/", "exp": 0, "happiness": 0, "pkdx_id": 682, "growth_rate": "", "species": "", "evolutions": [{"resource_uri": "/api/v1/pokemon/683/", "method": "trade", "to": "Aromatisse"}], "descriptions": [{"resource_uri": "/api/v1/description/6537/", "name": "spritzee_gen_6"}, {"resource_uri": "/api/v1/description/6538/", "name": "spritzee_gen_6"}], "attack": 52, "total": 0, "modified": "2013-11-23T13:13:47.576918", "sp_def": 65, "created": "2013-11-03T15:05:42.433633", "national_id": 682}