{"sprites": [{"resource_uri": "/api/v1/sprite/560/", "name": "scraggy"}], "ev_yield": "", "defense": 70, "height": "6", "hp": 50, "weight": "118", "catch_rate": 0, "abilities": [{"resource_uri": "/api/v1/ability/22/", "name": "intimidate"}, {"resource_uri": "/api/v1/ability/61/", "name": "shed-skin"}, {"resource_uri": "/api/v1/ability/153/", "name": "moxie"}], "sp_atk": 35, "name": "Scraggy", "moves": [{"resource_uri": "/api/v1/move/530/", "learn_type": "tutor", "name": "Dual-chop"}, {"resource_uri": "/api/v1/move/492/", "learn_type": "tutor", "name": "Foul-play"}, {"resource_uri": "/api/v1/move/442/", "learn_type": "tutor", "name": "Iron-head"}, {"resource_uri": "/api/v1/move/406/", "learn_type": "tutor", "name": "Dragon-pulse"}, {"resource_uri": "/api/v1/move/399/", "learn_type": "tutor", "name": "Dark-pulse"}, {"resource_uri": "/api/v1/move/334/", "learn_type": "tutor", "name": "Iron-defense"}, {"resource_uri": "/api/v1/move/289/", "learn_type": "tutor", "name": "Snatch"}, {"resource_uri": "/api/v1/move/282/", "learn_type": "tutor", "name": "Knock-off"}, {"resource_uri": "/api/v1/move/231/", "learn_type": "tutor", "name": "Iron-tail"}, {"resource_uri": "/api/v1/move/214/", "learn_type": "tutor", "name": "Sleep-talk"}, {"resource_uri": "/api/v1/move/180/", "learn_type": "tutor", "name": "Spite"}, {"resource_uri": "/api/v1/move/173/", "learn_type": "tutor", "name": "Snore"}, {"resource_uri": "/api/v1/move/162/", "learn_type": "tutor", "name": "Super-fang"}, {"resource_uri": "/api/v1/move/555/", "learn_type": "machine", "name": "Snarl"}, {"resource_uri": "/api/v1/move/526/", "learn_type": "machine", "name": "Work-up"}, {"resource_uri": "/api/v1/move/525/", "learn_type": "machine", "name": "Dragon-tail"}, {"resource_uri": "/api/v1/move/514/", "learn_type": "machine", "name": "Retaliate"}, {"resource_uri": "/api/v1/move/510/", "learn_type": "machine", "name": "Incinerate"}, {"resource_uri": "/api/v1/move/498/", "level": 27, "learn_type": "level up", "name": "Chip-away"}, {"resource_uri": "/api/v1/move/496/", "learn_type": "machine", "name": "Round"}, {"resource_uri": "/api/v1/move/490/", "learn_type": "machine", "name": "Low-sweep"}, {"resource_uri": "/api/v1/move/479/", "learn_type": "machine", "name": "Smack-down"}, {"resource_uri": "/api/v1/move/457/", "level": 53, "learn_type": "level up", "name": "Head-smash"}, {"resource_uri": "/api/v1/move/447/", "learn_type": "machine", "name": "Grass-knot"}, {"resource_uri": "/api/v1/move/444/", "learn_type": "machine", "name": "Stone-edge"}, {"resource_uri": "/api/v1/move/431/", "level": 45, "learn_type": "level up", "name": "Rock-climb"}, {"resource_uri": "/api/v1/move/428/", "learn_type": "egg move", "name": "Zen-headbutt"}, {"resource_uri": "/api/v1/move/411/", "learn_type": "machine", "name": "Focus-blast"}, {"resource_uri": "/api/v1/move/409/", "learn_type": "egg move", "name": "Drain-punch"}, {"resource_uri": "/api/v1/move/398/", "learn_type": "machine", "name": "Poison-jab"}, {"resource_uri": "/api/v1/move/374/", "learn_type": "machine", "name": "Fling"}, {"resource_uri": "/api/v1/move/371/", "level": 23, "learn_type": "level up", "name": "Payback"}, {"resource_uri": "/api/v1/move/349/", "learn_type": "egg move", "name": "Dragon-dance"}, {"resource_uri": "/api/v1/move/339/", "learn_type": "machine", "name": "Bulk-up"}, {"resource_uri": "/api/v1/move/337/", "learn_type": "machine", "name": "Dragon-claw"}, {"resource_uri": "/api/v1/move/317/", "learn_type": "machine", "name": "Rock-tomb"}, {"resource_uri": "/api/v1/move/280/", "level": 20, "learn_type": "level up", "name": "Brick-break"}, {"resource_uri": "/api/v1/move/269/", "learn_type": "machine", "name": "Taunt"}, {"resource_uri": "/api/v1/move/264/", "level": 49, "learn_type": "level up", "name": "Focus-punch"}, {"resource_uri": "/api/v1/move/263/", "level": 42, "learn_type": "level up", "name": "Facade"}, {"resource_uri": "/api/v1/move/259/", "learn_type": "machine", "name": "Torment"}, {"resource_uri": "/api/v1/move/252/", "learn_type": "egg move", "name": "Fake-out"}, {"resource_uri": "/api/v1/move/249/", "learn_type": "machine", "name": "Rock-smash"}, {"resource_uri": "/api/v1/move/242/", "level": 38, "learn_type": "level up", "name": "Crunch"}, {"resource_uri": "/api/v1/move/241/", "learn_type": "machine", "name": "Sunny-day"}, {"resource_uri": "/api/v1/move/240/", "learn_type": "machine", "name": "Rain-dance"}, {"resource_uri": "/api/v1/move/237/", "learn_type": "machine", "name": "Hidden-power"}, {"resource_uri": "/api/v1/move/218/", "learn_type": "machine", "name": "Frustration"}, {"resource_uri": "/api/v1/move/216/", "learn_type": "machine", "name": "Return"}, {"resource_uri": "/api/v1/move/213/", "learn_type": "machine", "name": "Attract"}, {"resource_uri": "/api/v1/move/207/", "level": 16, "learn_type": "level up", "name": "Swagger"}, {"resource_uri": "/api/v1/move/197/", "learn_type": "egg move", "name": "Detect"}, {"resource_uri": "/api/v1/move/188/", "learn_type": "machine", "name": "Sludge-bomb"}, {"resource_uri": "/api/v1/move/185/", "level": 9, "learn_type": "level up", "name": "Faint-attack"}, {"resource_uri": "/api/v1/move/184/", "level": 34, "learn_type": "level up", "name": "Scary-face"}, {"resource_uri": "/api/v1/move/182/", "learn_type": "machine", "name": "Protect"}, {"resource_uri": "/api/v1/move/164/", "learn_type": "machine", "name": "Substitute"}, {"resource_uri": "/api/v1/move/157/", "learn_type": "machine", "name": "Rock-slide"}, {"resource_uri": "/api/v1/move/156/", "learn_type": "machine", "name": "Rest"}, {"resource_uri": "/api/v1/move/136/", "level": 31, "learn_type": "level up", "name": "Hi-jump-kick"}, {"resource_uri": "/api/v1/move/133/", "learn_type": "egg move", "name": "Amnesia"}, {"resource_uri": "/api/v1/move/104/", "learn_type": "machine", "name": "Double-team"}, {"resource_uri": "/api/v1/move/92/", "learn_type": "machine", "name": "Toxic"}, {"resource_uri": "/api/v1/move/91/", "learn_type": "machine", "name": "Dig"}, {"resource_uri": "/api/v1/move/70/", "learn_type": "machine", "name": "Strength"}, {"resource_uri": "/api/v1/move/68/", "learn_type": "egg move", "name": "Counter"}, {"resource_uri": "/api/v1/move/67/", "level": 1, "learn_type": "level up", "name": "Low-kick"}, {"resource_uri": "/api/v1/move/46/", "learn_type": "machine", "name": "Roar"}, {"resource_uri": "/api/v1/move/43/", "level": 1, "learn_type": "level up", "name": "Leer"}, {"resource_uri": "/api/v1/move/29/", "level": 12, "learn_type": "level up", "name": "Headbutt"}, {"resource_uri": "/api/v1/move/28/", "level": 5, "learn_type": "level up", "name": "Sand-attack"}, {"resource_uri": "/api/v1/move/9/", "learn_type": "egg move", "name": "Thunderpunch"}, {"resource_uri": "/api/v1/move/8/", "learn_type": "egg move", "name": "Ice-punch"}, {"resource_uri": "/api/v1/move/7/", "learn_type": "egg move", "name": "Fire-punch"}], "speed": 48, "egg_cycles": 0, "types": [{"resource_uri": "/api/v1/type/2/", "name": "fighting"}, {"resource_uri": "/api/v1/type/17/", "name": "dark"}], "egg_groups": [{"resource_uri": "/api/v1/egg/5/", "name": "Ground"}, {"resource_uri": "/api/v1/egg/14/", "name": "Dragon"}], "male_female_ratio": "", "resource_uri": "/api/v1/pokemon/559/", "exp": 70, "happiness": 0, "pkdx_id": 559, "growth_rate": "", "species": "", "evolutions": [{"resource_uri": "/api/v1/pokemon/560/", "method": "level_up", "level": 39, "to": "Scrafty"}], "descriptions": [{"resource_uri": "/api/v1/description/6113/", "name": "scraggy_gen_4"}, {"resource_uri": "/api/v1/description/6114/", "name": "scraggy_gen_4"}, {"resource_uri": "/api/v1/description/6116/", "name": "scraggy_gen_6"}, {"resource_uri": "/api/v1/description/6115/", "name": "scraggy_gen_5"}, {"resource_uri": "/api/v1/description/6117/", "name": "scraggy_gen_6"}], "attack": 75, "total": 0, "modified": "2013-11-23T13:13:43.142836", "sp_def": 70, "created": "2013-11-03T15:05:42.245886", "national_id": 559}