{"sprites": [{"resource_uri": "/api/v1/sprite/119/", "name": "goldeen"}], "ev_yield": "", "defense": 60, "height": "6", "hp": 45, "weight": "150", "catch_rate": 0, "abilities": [{"resource_uri": "/api/v1/ability/31/", "name": "lightningrod"}, {"resource_uri": "/api/v1/ability/33/", "name": "swift-swim"}, {"resource_uri": "/api/v1/ability/41/", "name": "water-veil"}], "sp_atk": 35, "name": "Goldeen", "moves": [{"resource_uri": "/api/v1/move/529/", "learn_type": "tutor", "name": "Drill-run"}, {"resource_uri": "/api/v1/move/503/", "learn_type": "machine", "name": "Scald"}, {"resource_uri": "/api/v1/move/496/", "learn_type": "machine", "name": "Round"}, {"resource_uri": "/api/v1/move/487/", "level": 51, "learn_type": "level up", "name": "Soak"}, {"resource_uri": "/api/v1/move/341/", "learn_type": "egg move", "name": "Mud-shot"}, {"resource_uri": "/api/v1/move/324/", "learn_type": "egg move", "name": "Signal-beam"}, {"resource_uri": "/api/v1/move/250/", "learn_type": "machine", "name": "Whirlpool"}, {"resource_uri": "/api/v1/move/34/", "learn_type": "egg move", "name": "Body-slam"}, {"resource_uri": "/api/v1/move/340/", "learn_type": "tutor", "name": "Bounce"}, {"resource_uri": "/api/v1/move/282/", "learn_type": "tutor", "name": "Knock-off"}, {"resource_uri": "/api/v1/move/210/", "learn_type": "tutor", "name": "Fury-cutter"}, {"resource_uri": "/api/v1/move/445/", "learn_type": "machine", "name": "Captivate"}, {"resource_uri": "/api/v1/move/401/", "learn_type": "egg move", "name": "Aqua-tail"}, {"resource_uri": "/api/v1/move/398/", "learn_type": "machine", "name": "Poison-jab"}, {"resource_uri": "/api/v1/move/392/", "level": 27, "learn_type": "level up", "name": "Aqua-ring"}, {"resource_uri": "/api/v1/move/363/", "learn_type": "machine", "name": "Natural-gift"}, {"resource_uri": "/api/v1/move/189/", "learn_type": "egg move", "name": "Mud-slap"}, {"resource_uri": "/api/v1/move/224/", "level": 57, "learn_type": "level up", "name": "Megahorn"}, {"resource_uri": "/api/v1/move/352/", "learn_type": "machine", "name": "Water-pulse"}, {"resource_uri": "/api/v1/move/346/", "level": 1, "learn_type": "level up", "name": "Water-sport"}, {"resource_uri": "/api/v1/move/300/", "learn_type": "egg move", "name": "Mud-sport"}, {"resource_uri": "/api/v1/move/291/", "learn_type": "machine", "name": "Dive"}, {"resource_uri": "/api/v1/move/290/", "learn_type": "machine", "name": "Secret-power"}, {"resource_uri": "/api/v1/move/263/", "learn_type": "machine", "name": "Facade"}, {"resource_uri": "/api/v1/move/258/", "learn_type": "machine", "name": "Hail"}, {"resource_uri": "/api/v1/move/240/", "learn_type": "machine", "name": "Rain-dance"}, {"resource_uri": "/api/v1/move/237/", "learn_type": "machine", "name": "Hidden-power"}, {"resource_uri": "/api/v1/move/218/", "learn_type": "machine", "name": "Frustration"}, {"resource_uri": "/api/v1/move/216/", "learn_type": "machine", "name": "Return"}, {"resource_uri": "/api/v1/move/214/", "learn_type": "machine", "name": "Sleep-talk"}, {"resource_uri": "/api/v1/move/213/", "learn_type": "machine", "name": "Attract"}, {"resource_uri": "/api/v1/move/207/", "learn_type": "machine", "name": "Swagger"}, {"resource_uri": "/api/v1/move/203/", "learn_type": "machine", "name": "Endure"}, {"resource_uri": "/api/v1/move/196/", "learn_type": "machine", "name": "Icy-wind"}, {"resource_uri": "/api/v1/move/182/", "learn_type": "machine", "name": "Protect"}, {"resource_uri": "/api/v1/move/175/", "level": 24, "learn_type": "level up", "name": "Flail"}, {"resource_uri": "/api/v1/move/174/", "learn_type": "machine", "name": "Curse"}, {"resource_uri": "/api/v1/move/173/", "learn_type": "machine", "name": "Snore"}, {"resource_uri": "/api/v1/move/114/", "learn_type": "egg move", "name": "Haze"}, {"resource_uri": "/api/v1/move/60/", "learn_type": "egg move", "name": "Psybeam"}, {"resource_uri": "/api/v1/move/56/", "learn_type": "egg move", "name": "Hydro-pump"}, {"resource_uri": "/api/v1/move/164/", "learn_type": "machine", "name": "Substitute"}, {"resource_uri": "/api/v1/move/156/", "learn_type": "machine", "name": "Rest"}, {"resource_uri": "/api/v1/move/130/", "learn_type": "machine", "name": "Skull-bash"}, {"resource_uri": "/api/v1/move/129/", "learn_type": "machine", "name": "Swift"}, {"resource_uri": "/api/v1/move/127/", "level": 37, "learn_type": "level up", "name": "Waterfall"}, {"resource_uri": "/api/v1/move/117/", "learn_type": "machine", "name": "Bide"}, {"resource_uri": "/api/v1/move/104/", "learn_type": "machine", "name": "Double-team"}, {"resource_uri": "/api/v1/move/102/", "learn_type": "machine", "name": "Mimic"}, {"resource_uri": "/api/v1/move/99/", "learn_type": "machine", "name": "Rage"}, {"resource_uri": "/api/v1/move/97/", "level": 54, "learn_type": "level up", "name": "Agility"}, {"resource_uri": "/api/v1/move/92/", "learn_type": "machine", "name": "Toxic"}, {"resource_uri": "/api/v1/move/64/", "level": 1, "learn_type": "level up", "name": "Peck"}, {"resource_uri": "/api/v1/move/61/", "learn_type": "machine", "name": "Bubblebeam"}, {"resource_uri": "/api/v1/move/59/", "learn_type": "machine", "name": "Blizzard"}, {"resource_uri": "/api/v1/move/58/", "learn_type": "machine", "name": "Ice-beam"}, {"resource_uri": "/api/v1/move/57/", "learn_type": "machine", "name": "Surf"}, {"resource_uri": "/api/v1/move/55/", "learn_type": "machine", "name": "Water-gun"}, {"resource_uri": "/api/v1/move/48/", "level": 19, "learn_type": "level up", "name": "Supersonic"}, {"resource_uri": "/api/v1/move/39/", "level": 1, "learn_type": "level up", "name": "Tail-whip"}, {"resource_uri": "/api/v1/move/38/", "learn_type": "machine", "name": "Double-edge"}, {"resource_uri": "/api/v1/move/36/", "learn_type": "machine", "name": "Take-down"}, {"resource_uri": "/api/v1/move/32/", "level": 45, "learn_type": "level up", "name": "Horn-drill"}, {"resource_uri": "/api/v1/move/31/", "level": 30, "learn_type": "level up", "name": "Fury-attack"}, {"resource_uri": "/api/v1/move/30/", "level": 24, "learn_type": "level up", "name": "Horn-attack"}], "speed": 63, "egg_cycles": 0, "types": [{"resource_uri": "/api/v1/type/11/", "name": "water"}], "egg_groups": [{"resource_uri": "/api/v1/egg/12/", "name": "Water2"}], "male_female_ratio": "", "resource_uri": "/api/v1/pokemon/118/", "exp": 64, "happiness": 0, "pkdx_id": 118, "growth_rate": "", "species": "", "evolutions": [{"resource_uri": "/api/v1/pokemon/119/", "method": "level_up", "level": 33, "to": "Seaking"}], "descriptions": [{"resource_uri": "/api/v1/description/1923/", "name": "goldeen_gen_1"}, {"resource_uri": "/api/v1/description/1924/", "name": "goldeen_gen_1"}, {"resource_uri": "/api/v1/description/1925/", "name": "goldeen_gen_1"}, {"resource_uri": "/api/v1/description/1926/", "name": "goldeen_gen_1"}, {"resource_uri": "/api/v1/description/1927/", "name": "goldeen_gen_1"}, {"resource_uri": "/api/v1/description/1930/", "name": "goldeen_gen_2"}, {"resource_uri": "/api/v1/description/1931/", "name": "goldeen_gen_3"}, {"resource_uri": "/api/v1/description/1932/", "name": "goldeen_gen_3"}, {"resource_uri": "/api/v1/description/1933/", "name": "goldeen_gen_3"}, {"resource_uri": "/api/v1/description/1934/", "name": "goldeen_gen_3"}, {"resource_uri": "/api/v1/description/1935/", "name": "goldeen_gen_3"}, {"resource_uri": "/api/v1/description/1936/", "name": "goldeen_gen_4"}, {"resource_uri": "/api/v1/description/1937/", "name": "goldeen_gen_4"}, {"resource_uri": "/api/v1/description/1938/", "name": "goldeen_gen_4"}, {"resource_uri": "/api/v1/description/1939/", "name": "goldeen_gen_5"}, {"resource_uri": "/api/v1/description/1940/", "name": "goldeen_gen_6"}, {"resource_uri": "/api/v1/description/1941/", "name": "goldeen_gen_6"}, {"resource_uri": "/api/v1/description/1929/", "name": "goldeen_gen_2"}, {"resource_uri": "/api/v1/description/1928/", "name": "goldeen_gen_2"}], "attack": 67, "total": 0, "modified": "2013-11-23T13:13:27.606308", "sp_def": 50, "created": "2013-11-03T15:05:41.500000", "national_id": 118}