{"sprites": [{"resource_uri": "/api/v1/sprite/676/", "name": "pangoro"}], "ev_yield": "", "defense": 78, "height": "0", "hp": 95, "weight": "0", "catch_rate": 0, "abilities": [{"resource_uri": "/api/v1/ability/89/", "name": "iron-fist"}, {"resource_uri": "/api/v1/ability/104/", "name": "mold-breaker"}, {"resource_uri": "/api/v1/ability/113/", "name": "scrappy"}], "sp_atk": 69, "name": "Pangoro", "moves": [], "speed": 58, "egg_cycles": 0, "types": [{"resource_uri": "/api/v1/type/2/", "name": "fighting"}, {"resource_uri": "/api/v1/type/17/", "name": "dark"}], "egg_groups": [{"resource_uri": "/api/v1/egg/5/", "name": "Ground"}, {"resource_uri": "/api/v1/egg/8/", "name": "Human-like"}], "male_female_ratio": "", "resource_uri": "/api/v1/pokemon/675/", "exp": 0, "happiness": 0, "pkdx_id": 675, "growth_rate": "", "species": "", "evolutions": [], "descriptions": [{"resource_uri": "/api/v1/description/6523/", "name": "pangoro_gen_6"}, {"resource_uri": "/api/v1/description/6524/", "name": "pangoro_gen_6"}], "attack": 124, "total": 0, "modified": "2013-11-23T13:13:47.327453", "sp_def": 71, "created": "2013-11-03T15:05:42.423514", "national_id": 675}